setup.py
pyDBCLI/__init__.py
pyDBCLI/helpers.py
pyDBCLI/utils.py
pyDBCLI.egg-info/PKG-INFO
pyDBCLI.egg-info/SOURCES.txt
pyDBCLI.egg-info/dependency_links.txt
pyDBCLI.egg-info/requires.txt
pyDBCLI.egg-info/top_level.txt
pyDBCLI/extras/__init__.py
pyDBCLI/extras/litecli.py
pyDBCLI/extras/odbc.py