Metadata-Version: 1.0
Name: pyDBCLI
Version: 0.1
Summary: Python database CLI lib
Home-page: http://github.com/1stvamp/pyDBCLI
Author: Wes Mason
Author-email: wes[at]1stvamp[dot]org
License: Apache License 2.0
Platform: UNKNOWN
